archeai/__init__.py
archeai/agent.py
archeai/taskforce.py
archeai/llms/Anthropic.py
archeai/llms/Cohere.py
archeai/llms/Gemini.py
archeai/llms/Groq.py
archeai/llms/OpenAI.py
archeai/llms/__init__.py
archeai/memory/__init__.py
archeai/tools/HTMLScraper.py
archeai/tools/__init__.py
archeai/tools/current_time.py
archeai/tools/tool.py
archeai/tools/websearch.py
archeai-0.0.7.dist-info/LICENSE
archeai-0.0.7.dist-info/METADATA
archeai-0.0.7.dist-info/WHEEL
archeai-0.0.7.dist-info/top_level.txt
archeai-0.0.7.dist-info/RECORD
