Metadata-Version: 2.1
Name: archeai
Version: 0.0.7
Summary: ArcheAI is a lightweight and scalable Python agent framework that simplifies AI agent development.  Build smarter, more capable agents with ease using ArcheAI's easy tool integration, LLM interaction, and agent orchestration.
Author: E5Anant (Anant Sharma)
Author-email: e5anant2011@gmail.com
Keywords: agents,archeai,archeAI,multi-agent,taskforce,python,light-weight,agent-framework,framework
Classifier: Development Status :: 1 - Planning
Classifier: Intended Audience :: Developers
Classifier: Programming Language :: Python :: 3
Classifier: Operating System :: Unix
Classifier: Operating System :: MacOS :: MacOS X
Classifier: Operating System :: Microsoft :: Windows
License-File: LICENSE
Requires-Dist: cohere
Requires-Dist: groq
Requires-Dist: rich==12.6.0
Requires-Dist: python-dotenv==1.0.1
Requires-Dist: google-generativeai
Requires-Dist: requests==2.31.0
Requires-Dist: colorama==0.4.6
Requires-Dist: googlesearch-python==1.2.4
Requires-Dist: yfinance==0.2.41
Requires-Dist: bs4==0.0.1
Requires-Dist: anthropic
Requires-Dist: openai
Requires-Dist: scikit-learn==1.5.2
